[
  {
    "Id": 110001,
    "Name": "castname_110001",
    "Desc": "castdesc_110001",
    "TotalTime": 0,
    "SelectTargetType": 1,
    "CastSelectTargetsParam": {
      "$type": "CastSingle"
    },
    "NotifyType": 2,
    "HitInfos": [
      {
        "Time": 0,
        "HitSelf": false,
        "HitAction": 1001,
        "TargetBuff": 2001,
        "SelfBuff": 2001
      },
      {
        "Time": 1000,
        "HitSelf": true,
        "HitAction": 1001,
        "TargetBuff": 2001,
        "SelfBuff": 2001
      }
    ]
  },
  {
    "Id": 110002,
    "Name": "castname_110002",
    "Desc": "castdesc_110002",
    "TotalTime": 0,
    "SelectTargetType": 1,
    "CastSelectTargetsParam": {
      "$type": "CastSingle"
    },
    "NotifyType": 2,
    "HitInfos": []
  },
  {
    "Id": 110003,
    "Name": "castname_110003",
    "Desc": "castdesc_110003",
    "TotalTime": 0,
    "SelectTargetType": 1,
    "CastSelectTargetsParam": {
      "$type": "CastSingle"
    },
    "NotifyType": 2,
    "HitInfos": []
  },
  {
    "Id": 110004,
    "Name": "castname_110004",
    "Desc": "castdesc_110004",
    "TotalTime": 0,
    "SelectTargetType": 1,
    "CastSelectTargetsParam": {
      "$type": "CastSingle"
    },
    "NotifyType": 2,
    "HitInfos": []
  },
  {
    "Id": 110005,
    "Name": "castname_110005",
    "Desc": "castdesc_110005",
    "TotalTime": 0,
    "SelectTargetType": 1,
    "CastSelectTargetsParam": {
      "$type": "CastSingle"
    },
    "NotifyType": 2,
    "HitInfos": []
  },
  {
    "Id": 120001,
    "Name": "castname_120001",
    "Desc": "castdesc_120001",
    "TotalTime": 0,
    "SelectTargetType": 2,
    "CastSelectTargetsParam": {
      "$type": "CastTargetCycle",
      "IncludeSelf": false,
      "Radius": 5,
      "Counter": 5
    },
    "NotifyType": 2,
    "HitInfos": []
  },
  {
    "Id": 120002,
    "Name": "castname_120002",
    "Desc": "castdesc_120002",
    "TotalTime": 0,
    "SelectTargetType": 2,
    "CastSelectTargetsParam": {
      "$type": "CastTargetCycle",
      "IncludeSelf": false,
      "Radius": 5,
      "Counter": 5
    },
    "NotifyType": 2,
    "HitInfos": []
  },
  {
    "Id": 120003,
    "Name": "castname_120003",
    "Desc": "castdesc_120003",
    "TotalTime": 0,
    "SelectTargetType": 2,
    "CastSelectTargetsParam": {
      "$type": "CastTargetCycle",
      "IncludeSelf": false,
      "Radius": 5,
      "Counter": 5
    },
    "NotifyType": 2,
    "HitInfos": []
  },
  {
    "Id": 120004,
    "Name": "castname_120004",
    "Desc": "castdesc_120004",
    "TotalTime": 0,
    "SelectTargetType": 2,
    "CastSelectTargetsParam": {
      "$type": "CastTargetCycle",
      "IncludeSelf": false,
      "Radius": 5,
      "Counter": 5
    },
    "NotifyType": 2,
    "HitInfos": []
  },
  {
    "Id": 120005,
    "Name": "castname_120005",
    "Desc": "castdesc_120005",
    "TotalTime": 0,
    "SelectTargetType": 2,
    "CastSelectTargetsParam": {
      "$type": "CastTargetCycle",
      "IncludeSelf": false,
      "Radius": 5,
      "Counter": 5
    },
    "NotifyType": 2,
    "HitInfos": []
  },
  {
    "Id": 130001,
    "Name": "castname_130001",
    "Desc": "castdesc_130001",
    "TotalTime": 0,
    "SelectTargetType": 3,
    "CastSelectTargetsParam": {
      "$type": "CastForwardRect",
      "Width": 3,
      "Height": 6,
      "Counter": 5
    },
    "NotifyType": 2,
    "HitInfos": []
  },
  {
    "Id": 130002,
    "Name": "castname_130002",
    "Desc": "castdesc_130002",
    "TotalTime": 0,
    "SelectTargetType": 3,
    "CastSelectTargetsParam": {
      "$type": "CastForwardRect",
      "Width": 3,
      "Height": 6,
      "Counter": 5
    },
    "NotifyType": 2,
    "HitInfos": []
  },
  {
    "Id": 130003,
    "Name": "castname_130003",
    "Desc": "castdesc_130003",
    "TotalTime": 0,
    "SelectTargetType": 3,
    "CastSelectTargetsParam": {
      "$type": "CastForwardRect",
      "Width": 3,
      "Height": 6,
      "Counter": 5
    },
    "NotifyType": 2,
    "HitInfos": []
  },
  {
    "Id": 130004,
    "Name": "castname_130004",
    "Desc": "castdesc_130004",
    "TotalTime": 0,
    "SelectTargetType": 3,
    "CastSelectTargetsParam": {
      "$type": "CastForwardRect",
      "Width": 3,
      "Height": 6,
      "Counter": 5
    },
    "NotifyType": 2,
    "HitInfos": []
  },
  {
    "Id": 130005,
    "Name": "castname_130005",
    "Desc": "castdesc_130005",
    "TotalTime": 0,
    "SelectTargetType": 3,
    "CastSelectTargetsParam": {
      "$type": "CastForwardRect",
      "Width": 3,
      "Height": 6,
      "Counter": 5
    },
    "NotifyType": 2,
    "HitInfos": []
  }
]